xcute/__init__.py
xcute/utils.py
pyxcute-0.8.1.dist-info/METADATA
pyxcute-0.8.1.dist-info/WHEEL
pyxcute-0.8.1.dist-info/entry_points.txt
pyxcute-0.8.1.dist-info/top_level.txt
pyxcute-0.8.1.dist-info/zip-safe
pyxcute-0.8.1.dist-info/RECORD
