Metadata-Version: 2.1
Name: pyxcute
Version: 0.8.1
Summary: A small task runner inspired by npm scripts.
Home-page: https://github.com/eight04/pyXcute
Author: eight
Author-email: eight04@gmail.com
License: MIT
Keywords: run,task,runner,execute,bump,bumper,build,tool,npm
Classifier: Development Status :: 5 - Production/Stable
Classifier: Environment :: Console
Classifier: Intended Audience :: Developers
Classifier: License :: OSI Approved :: MIT License
Classifier: Natural Language :: Chinese (Traditional)
Classifier: Programming Language :: Python :: 3.7
Classifier: Programming Language :: Python :: 3.8
Classifier: Programming Language :: Python :: 3.9
Classifier: Programming Language :: Python :: 3.10
Classifier: Programming Language :: Python :: 3.11
Classifier: Programming Language :: Python :: 3.12
Classifier: Topic :: Software Development :: Libraries :: Python Modules
Classifier: Topic :: Software Development :: Build Tools
Requires-Dist: livereload ~=2.6
Requires-Dist: ordered-set ~=3.1
Requires-Dist: semver ~=2.9
Requires-Dist: send2trash ~=1.5
